[
{
  "elements": [
    {
      "keyword": "Scenario",
      "location": "features\\first_selenium.feature:3",
      "name": "Login to the demo website",
      "steps": [
        {
          "keyword": "Given",
          "location": "features\\first_selenium.feature:4",
          "match": {
            "arguments": [],
            "location": "features\\steps\\reusableSteps.py:18"
          },
          "name": "the user is on login page",
          "result": {
            "duration": 0.01604604721069336,
            "status": "passed"
          },
          "step_type": "given"
        },
        {
          "keyword": "When",
          "location": "features\\first_selenium.feature:5",
          "match": {
            "arguments": [],
            "location": "features\\steps\\first_selenium.py:15"
          },
          "name": "the user enters the credentials and logs in",
          "result": {
            "duration": 3.389582633972168,
            "status": "passed"
          },
          "step_type": "when"
        },
        {
          "keyword": "Then",
          "location": "features\\first_selenium.feature:6",
          "match": {
            "arguments": [],
            "location": "features\\steps\\reusableSteps.py:27"
          },
          "name": "he should land on the correct page",
          "result": {
            "duration": 0.022058963775634766,
            "status": "passed"
          },
          "step_type": "then"
        }
      ],
      "tags": [],
      "type": "scenario"
    },
    {
      "keyword": "Scenario",
      "location": "features\\first_selenium.feature:8",
      "name": "Navigate to user profile page",
      "steps": [
        {
          "keyword": "Given",
          "location": "features\\first_selenium.feature:9",
          "match": {
            "arguments": [],
            "location": "features\\steps\\reusableSteps.py:37"
          },
          "name": "the user is on dashboard page",
          "result": {
            "duration": 0.006017208099365234,
            "status": "passed"
          },
          "step_type": "given"
        },
        {
          "keyword": "When",
          "location": "features\\first_selenium.feature:10",
          "match": {
            "arguments": [],
            "location": "features\\steps\\first_selenium.py:22"
          },
          "name": "user clicks the user profile icon",
          "result": {
            "duration": 3.076490640640259,
            "status": "passed"
          },
          "step_type": "when"
        },
        {
          "keyword": "Then",
          "location": "features\\first_selenium.feature:11",
          "match": {
            "arguments": [],
            "location": "features\\steps\\reusableSteps.py:46"
          },
          "name": "he should land on the correct profile page",
          "result": {
            "duration": 0.018049955368041992,
            "status": "passed"
          },
          "step_type": "then"
        }
      ],
      "tags": [],
      "type": "scenario"
    }
  ],
  "keyword": "Feature",
  "location": "features\\first_selenium.feature:1",
  "name": "As a user I want to test the login functionality and much more",
  "status": "passed",
  "tags": []
}
]
